iflow_mcp_mcp_safe_local_python_executor-0.1.0.dist-info/licenses/LICENSE
tests/test_local_python_executor.py
tests/test_mcp_server.py
iflow_mcp_mcp_safe_local_python_executor-0.1.0.dist-info/METADATA
iflow_mcp_mcp_safe_local_python_executor-0.1.0.dist-info/WHEEL
iflow_mcp_mcp_safe_local_python_executor-0.1.0.dist-info/entry_points.txt
iflow_mcp_mcp_safe_local_python_executor-0.1.0.dist-info/top_level.txt
iflow_mcp_mcp_safe_local_python_executor-0.1.0.dist-info/RECORD
