Metadata-Version: 2.4
Name: iflow-mcp_mcp_safe_local_python_executor
Version: 0.1.0
Summary: MCP server exposing tool for a safe local Python code execution
Author: Maxim Saplin
License: MIT
Project-URL: Homepage, https://github.com/maxim-saplin/mcp_safe_local_python_executor/tree/main
Classifier: Development Status :: 3 - Alpha
Classifier: Intended Audience :: Developers
Classifier: Topic :: Software Development :: Libraries :: Python Modules
Classifier: Programming Language :: Python :: 3.10
Classifier: Programming Language :: Python :: 3.11
Classifier: Programming Language :: Python :: 3.12
Classifier: Programming Language :: Python :: 3.13
Classifier: Operating System :: OS Independent
Requires-Python: >=3.10
License-File: LICENSE
Requires-Dist: mcp[cli]>=1.5.0
Requires-Dist: smolagents==1.12.0
Dynamic: license-file
